FPGA_Projects20250804/ModesimTest/counter_sub.v
module counter_sub (
    input        clk,      // 时钟输入（50MHz）
    input        rst_n,    // 复位输入（低电平有效）
    output  [3:0] count_out  // 4位计数器输出
);

// 内部信号：计数器寄存器（可在ModelSim中观测）
reg [3:0] count_reg;

// 计数器逻辑
always @(posedge clk or negedge rst_n) begin
    if (!rst_n) begin
        count_reg <= 4'd0;       // 复位时清零
    end else begin
        count_reg <= count_reg + 1'b1;  // 时钟上升沿计数递增
    end
end

// 输出赋值
assign count_out = count_reg;

endmodule

FPGA_Projects20250804/ModesimTest/simple_top.v
module simple_top (
    input        clk,      // 系统时钟（50MHz）
    input        rst_n,    // 系统复位（低电平有效）
    output [3:0] led_out   // LED输出（连接计数器输出）
);

// 内部信号：连接子模块的中间信号（可观测）
wire [3:0] count_wire;

// 实例化子模块（计数器）
counter_sub u_counter (
    .clk      (clk),       // 时钟连接
    .rst_n    (rst_n),     // 复位连接
    .count_out(count_wire) // 计数器输出连接到内部wire
);

// 顶层输出：将计数器值映射到LED
assign led_out = count_wire;

endmodule

FPGA_Projects20250804/ModesimTest/simple_top_tb.v
`timescale 1ns / 1ps

module simple_top_tb;

// 激励信号定义
reg clk;       // 测试时钟
reg rst_n;     // 测试复位
wire [3:0] led_out;  // 观测顶层输出

// 实例化顶层模块
simple_top uut (
    .clk      (clk),
    .rst_n    (rst_n),
    .led_out  (led_out)
);

// 生成时钟（50MHz，周期20ns）
initial begin
    clk = 0;
    forever #10 clk = ~clk;  // 每10ns翻转一次，周期20ns
end

// 生成复位信号
initial begin
    rst_n = 0;               // 初始复位
    #200 rst_n = 1;          // 200ns后释放复位
    #2000 $stop;           // 仿真2000ns后结束
end

// 可选：添加波形文件生成（若ModelSim未自动生成）
initial begin
    $dumpfile("waveform.vcd");  // 生成VCD波形文件
    $dumpvars(0, simple_top_tb); // 记录所有信号
end

endmodule

FPGA_Projects20250804/ModesimTest/simulation/questa/waveform.vcd
$date
	Sat Aug 16 22:24:48 2025
$end
$version
	ModelSim Version 2020.1
$end
$timescale
	1ps
$end

$scope module simple_top_tb $end
$var reg 1 ! clk $end
$var reg 1 " rst_n $end
$var wire 1 # led_out [3] $end
$var wire 1 $ led_out [2] $end
$var wire 1 % led_out [1] $end
$var wire 1 & led_out [0] $end

$scope module uut $end
$var wire 1 ' clk $end
$var wire 1 ( rst_n $end
$var wire 1 # led_out [3] $end
$var wire 1 $ led_out [2] $end
$var wire 1 % led_out [1] $end
$var wire 1 & led_out [0] $end
$var wire 1 ) count_wire [3] $end
$var wire 1 * count_wire [2] $end
$var wire 1 + count_wire [1] $end
$var wire 1 , count_wire [0] $end

$scope module u_counter $end
$var wire 1 ' clk $end
$var wire 1 ( rst_n $end
$var wire 1 ) count_out [3] $end
$var wire 1 * count_out [2] $end
$var wire 1 + count_out [1] $end
$var wire 1 , count_out [0] $end
$var reg 4 - count_reg [3:0] $end
$upscope $end
$upscope $end
$upscope $end
$enddefinitions $end
#0
$dumpvars
0!
0"
b0 -
0&
0%
0$
0#
0,
0+
0*
0)
0(
0'
$end
#10000
1!
1'
#20000
0!
0'
#30000
1!
1'
#40000
0!
0'
#50000
1!
1'
#60000
0!
0'
#70000
1!
1'
#80000
0!
0'
#90000
1!
1'
#100000
0!
0'
#110000
1!
1'
#120000
0!
0'
#130000
1!
1'
#140000
0!
0'
#150000
1!
1'
#160000
0!
0'
#170000
1!
1'
#180000
0!
0'
#190000
1!
1'
#200000
1"
0!
1(
0'
#210000
1!
1'
b1 -
1,
1&
#220000
0!
0'
#230000
1!
1'
b10 -
0,
1+
0&
1%
#240000
0!
0'
#250000
1!
1'
b11 -
1,
1&
#260000
0!
0'
#270000
1!
1'
b100 -
0,
0+
1*
0&
0%
1$
#280000
0!
0'
#290000
1!
1'
b101 -
1,
1&
#300000
0!
0'
#310000
1!
1'
b110 -
0,
1+
0&
1%
#320000
0!
0'
#330000
1!
1'
b111 -
1,
1&
#340000
0!
0'
#350000
1!
1'
b1000 -
0,
0+
0*
1)
0&
0%
0$
1#
#360000
0!
0'
#370000
1!
1'
b1001 -
1,
1&
#380000
0!
0'
#390000
1!
1'
b1010 -
0,
1+
0&
1%
#400000
0!
0'
#410000
1!
1'
b1011 -
1,
1&
#420000
0!
0'
#430000
1!
1'
b1100 -
0,
0+
1*
0&
0%
1$
#440000
0!
0'
#450000
1!
1'
b1101 -
1,
1&
#460000
0!
0'
#470000
1!
1'
b1110 -
0,
1+
0&
1%
#480000
0!
0'
#490000
1!
1'
b1111 -
1,
1&
#500000
0!
0'
#510000
1!
1'
b0 -
0,
0+
0*
0)
0&
0%
0$
0#
#520000
0!
0'
#530000
1!
1'
b1 -
1,
1&
#540000
0!
0'
#550000
1!
1'
b10 -
0,
1+
0&
1%
#560000
0!
0'
#570000
1!
1'
b11 -
1,
1&
#580000
0!
0'
#590000
1!
1'
b100 -
0,
0+
1*
0&
0%
1$
#600000
0!
0'
#610000
1!
1'
b101 -
1,
1&
#620000
0!
0'
#630000
1!
1'
b110 -
0,
1+
0&
1%
#640000
0!
0'
#650000
1!
1'
b111 -
1,
1&
#660000
0!
0'
#670000
1!
1'
b1000 -
0,
0+
0*
1)
0&
0%
0$
1#
#680000
0!
0'
#690000
1!
1'
b1001 -
1,
1&
#700000
0!
0'
#710000
1!
1'
b1010 -
0,
1+
0&
1%
#720000
0!
0'
#730000
1!
1'
b1011 -
1,
1&
#740000
0!
0'
#750000
1!
1'
b1100 -
0,
0+
1*
0&
0%
1$
#760000
0!
0'
#770000
1!
1'
b1101 -
1,
1&
#780000
0!
0'
#790000
1!
1'
b1110 -
0,
1+
0&
1%
#800000
0!
0'
#810000
1!
1'
b1111 -
1,
1&
#820000
0!
0'
#830000
1!
1'
b0 -
0,
0+
0*
0)
0&
0%
0$
0#
#840000
0!
0'
#850000
1!
1'
b1 -
1,
1&
#860000
0!
0'
#870000
1!
1'
b10 -
0,
1+
0&
1%
#880000
0!
0'
#890000
1!
1'
b11 -
1,
1&
#900000
0!
0'
#910000
1!
1'
b100 -
0,
0+
1*
0&
0%
1$
#920000
0!
0'
#930000
1!
1'
b101 -
1,
1&
#940000
0!
0'
#950000
1!
1'
b110 -
0,
1+
0&
1%
#960000
0!
0'
#970000
1!
1'
b111 -
1,
1&
#980000
0!
0'
#990000
1!
1'
b1000 -
0,
0+
0*
1)
0&
0%
0$
1#
#1000000
0!
0'
#1010000
1!
1'
b1001 -
1,
1&
#1020000
0!
0'
#1030000
1!
1'
b1010 -
0,
1+
0&
1%
#1040000
0!
0'
#1050000
1!
1'
b1011 -
1,
1&
#1060000
0!
0'
#1070000
1!
1'
b1100 -
0,
0+
1*
0&
0%
1$
#1080000
0!
0'
#1090000
1!
1'
b1101 -
1,
1&
#1100000
0!
0'
#1110000
1!
1'
b1110 -
0,
1+
0&
1%
#1120000
0!
0'
#1130000
1!
1'
b1111 -
1,
1&
#1140000
0!
0'
#1150000
1!
1'
b0 -
0,
0+
0*
0)
0&
0%
0$
0#
#1160000
0!
0'
#1170000
1!
1'
b1 -
1,
1&
#1180000
0!
0'
#1190000
1!
1'
b10 -
0,
1+
0&
1%
#1200000
0!
0'
#1210000
1!
1'
b11 -
1,
1&
#1220000
0!
0'
#1230000
1!
1'
b100 -
0,
0+
1*
0&
0%
1$
#1240000
0!
0'
#1250000
1!
1'
b101 -
1,
1&
#1260000
0!
0'
#1270000
1!
1'
b110 -
0,
1+
0&
1%
#1280000
0!
0'
#1290000
1!
1'
b111 -
1,
1&
#1300000
0!
0'
#1310000
1!
1'
b1000 -
0,
0+
0*
1)
0&
0%
0$
1#
#1320000
0!
0'
#1330000
1!
1'
b1001 -
1,
1&
#1340000
0!
0'
#1350000
1!
1'
b1010 -
0,
1+
0&
1%
#1360000
0!
0'
#1370000
1!
1'
b1011 -
1,
1&
#1380000
0!
0'
#1390000
1!
1'
b1100 -
0,
0+
1*
0&
0%
1$
#1400000
0!
0'
#1410000
1!
1'
b1101 -
1,
1&
#1420000
0!
0'
#1430000
1!
1'
b1110 -
0,
1+
0&
1%
#1440000
0!
0'
#1450000
1!
1'
b1111 -
1,
1&
#1460000
0!
0'
#1470000
1!
1'
b0 -
0,
0+
0*
0)
0&
0%
0$
0#
#1480000
0!
0'
#1490000
1!
1'
b1 -
1,
1&
#1500000
0!
0'
#1510000
1!
1'
b10 -
0,
1+
0&
1%
#1520000
0!
0'
#1530000
1!
1'
b11 -
1,
1&
#1540000
0!
0'
#1550000
1!
1'
b100 -
0,
0+
1*
0&
0%
1$
#1560000
0!
0'
#1570000
1!
1'
b101 -
1,
1&
#1580000
0!
0'
#1590000
1!
1'
b110 -
0,
1+
0&
1%
#1600000
0!
0'
#1610000
1!
1'
b111 -
1,
1&
#1620000
0!
0'
#1630000
1!
1'
b1000 -
0,
0+
0*
1)
0&
0%
0$
1#
#1640000
0!
0'
#1650000
1!
1'
b1001 -
1,
1&
#1660000
0!
0'
#1670000
1!
1'
b1010 -
0,
1+
0&
1%
#1680000
0!
0'
#1690000
1!
1'
b1011 -
1,
1&
#1700000
0!
0'
#1710000
1!
1'
b1100 -
0,
0+
1*
0&
0%
1$
#1720000
0!
0'
#1730000
1!
1'
b1101 -
1,
1&
#1740000
0!
0'
#1750000
1!
1'
b1110 -
0,
1+
0&
1%
#1760000
0!
0'
#1770000
1!
1'
b1111 -
1,
1&
#1780000
0!
0'
#1790000
1!
1'
b0 -
0,
0+
0*
0)
0&
0%
0$
0#
#1800000
0!
0'
#1810000
1!
1'
b1 -
1,
1&
#1820000
0!
0'
#1830000
1!
1'
b10 -
0,
1+
0&
1%
#1840000
0!
0'
#1850000
1!
1'
b11 -
1,
1&
#1860000
0!
0'
#1870000
1!
1'
b100 -
0,
0+
1*
0&
0%
1$
#1880000
0!
0'
#1890000
1!
1'
b101 -
1,
1&
#1900000
0!
0'
#1910000
1!
1'
b110 -
0,
1+
0&
1%
#1920000
0!
0'
#1930000
1!
1'
b111 -
1,
1&
#1940000
0!
0'
#1950000
1!
1'
b1000 -
0,
0+
0*
1)
0&
0%
0$
1#
#1960000
0!
0'
#1970000
1!
1'
b1001 -
1,
1&
#1980000
0!
0'
#1990000
1!
1'
b1010 -
0,
1+
0&
1%
#2000000
0!
0'
#2010000
1!
1'
b1011 -
1,
1&
#2020000
0!
0'
#2030000
1!
1'
b1100 -
0,
0+
1*
0&
0%
1$
#2040000
0!
0'
#2050000
1!
1'
b1101 -
1,
1&
#2060000
0!
0'
#2070000
1!
1'
b1110 -
0,
1+
0&
1%
#2080000
0!
0'
#2090000
1!
1'
b1111 -
1,
1&
#2100000
0!
0'
#2110000
1!
1'
b0 -
0,
0+
0*
0)
0&
0%
0$
0#
#2120000
0!
0'
#2130000
1!
1'
b1 -
1,
1&
#2140000
0!
0'
#2150000
1!
1'
b10 -
0,
1+
0&
1%
#2160000
0!
0'
#2170000
1!
1'
b11 -
1,
1&
#2180000
0!
0'
#2190000
1!
1'
b100 -
0,
0+
1*
0&
0%
1$
